short_text_field/__init__.py
short_text_field/admin.py
short_text_field/apps.py
short_text_field/models.py
short_text_field/tests/__init__.py
short_text_field/tests/__main__.py
short_text_field/tests/models.py
short_text_field/tests/settings.py
short_text_field/tests/test_admin.py
short_text_field/tests/test_models.py
short_text_field/tests/tests.py
django_short_text_field_0.2-0.2.dist-info/LICENSE
django_short_text_field_0.2-0.2.dist-info/METADATA
django_short_text_field_0.2-0.2.dist-info/WHEEL
django_short_text_field_0.2-0.2.dist-info/top_level.txt
django_short_text_field_0.2-0.2.dist-info/RECORD
