Metadata-Version: 2.1
Name: django-short-text-field-0.2
Version: 0.2
Summary: A Django app which adds a ShortTextField model field, whichis like a TextField in the database and like a CharField informs.
Home-page: https://www.example.com/
Author: Andrew Foote
Author-email: footeandrew1@gmail.com
License: BSD License
Platform: UNKNOWN
Classifier: Environment :: Web Environment
Classifier: Framework :: Django
Classifier: Framework :: Django :: 2.1
Classifier: Intended Audience :: Developers
Classifier: License :: OSI Approved :: BSD License
Classifier: Operating System :: OS Independent
Classifier: Programming Language :: Python
Classifier: Programming Language :: Python :: 3.7
Classifier: Topic :: Internet :: WWW/HTTP
Classifier: Topic :: Internet :: WWW/HTTP :: Dynamic Content
